{
  "project_info": {
    "project_number": "264575307830",
    "project_id": "first-firebase-pro-2f4e2",
    "storage_bucket": "first-firebase-pro-2f4e2.firebasestorage.app"
  },
  "client": [
    {
      "client_info": {
        "mobilesdk_app_id": "1:264575307830:android:8fe83c673c4afb5c228897",
        "android_client_info": {
          "package_name": "com.example.furniture_app"
        }
      },
      "oauth_client": [],
      "api_key": [
        {
          "current_key": "AIzaSyDYi1Ud0LMzd4MinTwNoYFbvGOoWHlLsnM"
        }
      ],
      "services": {
        "appinvite_service": {
          "other_platform_oauth_client": []
        }
      }
    }
  ],
  "configuration_version": "1"
}